LICENSE
MANIFEST.in
README.rst
setup.py
supermjo/__init__.py
supermjo/supermjo.py
supermjo_py.egg-info/PKG-INFO
supermjo_py.egg-info/SOURCES.txt
supermjo_py.egg-info/dependency_links.txt
supermjo_py.egg-info/requires.txt
supermjo_py.egg-info/top_level.txt
test/test.py