Metadata-Version: 1.1
Name: supermjo-py
Version: 0.2.0
Summary: Python interface to Super-Mjograph
Home-page: https://github.com/moykeen/supermjo-py
Author: Makoto Tanahashi
Author-email: makoto.mjo@gmail.com
License: MIT
Keywords: graph plot visualization
Platform: UNKNOWN
Classifier: Operating System :: MacOS :: MacOS X
Classifier: License :: OSI Approved :: MIT License
Classifier: Programming Language :: Python
Classifier: Programming Language :: Python :: 3
Classifier: Programming Language :: Python :: 3.5
Classifier: Programming Language :: Python :: 3.6
Classifier: Intended Audience :: Science/Research
Classifier: Topic :: Scientific/Engineering :: Visualization
